drafter.py
drafter/__init__.py
drafter/__main__.py
drafter/command_line.py
drafter/components.py
drafter/configuration.py
drafter/constants.py
drafter/debug.py
drafter/deploy.py
drafter/files.py
drafter/hacks.py
drafter/history.py
drafter/image_support.py
drafter/llm.py
drafter/page.py
drafter/py.typed
drafter/raw_files.py
drafter/routes.py
drafter/server.py
drafter/setup.py
drafter/styling.py
drafter/testing.py
drafter/urls.py
drafter-1.9.5.dist-info/LICENSE.txt
drafter-1.9.5.dist-info/METADATA
drafter-1.9.5.dist-info/WHEEL
drafter-1.9.5.dist-info/entry_points.txt
drafter-1.9.5.dist-info/top_level.txt
drafter-1.9.5.dist-info/RECORD
