Metadata-Version: 2.1
Name: drafter
Version: 1.9.5
Summary: Student-friendly full stack web development library.
Home-page: https://github.com/drafter-edu/drafter
Author: acbart
Author-email: acbart@udel.edu
License: MIT
Classifier: Development Status :: 3 - Alpha
Classifier: Topic :: Education
Classifier: License :: OSI Approved :: MIT License
Classifier: Programming Language :: Python :: 3.7
Classifier: Programming Language :: Python :: 3.8
Classifier: Programming Language :: Python :: 3.9
Classifier: Programming Language :: Python :: 3.10
Classifier: Programming Language :: Python :: 3.11
Requires-Python: >=3.7
License-File: LICENSE.txt
Requires-Dist: bottle
Requires-Dist: bakery
